pulumi_digitalocean_native/__init__.py
pulumi_digitalocean_native/_utilities.py
pulumi_digitalocean_native/provider.py
pulumi_digitalocean_native/pulumi-plugin.json
pulumi_digitalocean_native/py.typed
pulumi_digitalocean_native/_1_clicks/__init__.py
pulumi_digitalocean_native/_1_clicks/v2/__init__.py
pulumi_digitalocean_native/_1_clicks/v2/list_one_clicks.py
pulumi_digitalocean_native/_1_clicks/v2/one_clicks_install_kubernetes.py
pulumi_digitalocean_native/_1_clicks/v2/outputs.py
pulumi_digitalocean_native/account/__init__.py
pulumi_digitalocean_native/account/v2/__init__.py
pulumi_digitalocean_native/account/v2/_enums.py
pulumi_digitalocean_native/account/v2/get_account.py
pulumi_digitalocean_native/account/v2/get_ssh_key.py
pulumi_digitalocean_native/account/v2/list_ssh_keys.py
pulumi_digitalocean_native/account/v2/outputs.py
pulumi_digitalocean_native/account/v2/ssh_key.py
pulumi_digitalocean_native/actions/__init__.py
pulumi_digitalocean_native/actions/v2/__init__.py
pulumi_digitalocean_native/actions/v2/_enums.py
pulumi_digitalocean_native/actions/v2/get_action.py
pulumi_digitalocean_native/actions/v2/list_actions.py
pulumi_digitalocean_native/actions/v2/outputs.py
pulumi_digitalocean_native/apps/__init__.py
pulumi_digitalocean_native/apps/v2/__init__.py
pulumi_digitalocean_native/apps/v2/_enums.py
pulumi_digitalocean_native/apps/v2/_inputs.py
pulumi_digitalocean_native/apps/v2/app.py
pulumi_digitalocean_native/apps/v2/apps_assign_alert_destination.py
pulumi_digitalocean_native/apps/v2/apps_deployment.py
pulumi_digitalocean_native/apps/v2/apps_list_metrics_bandwidth_daily.py
pulumi_digitalocean_native/apps/v2/apps_rollback.py
pulumi_digitalocean_native/apps/v2/apps_validate_app_spec.py
pulumi_digitalocean_native/apps/v2/apps_validate_rollback.py
pulumi_digitalocean_native/apps/v2/get_app.py
pulumi_digitalocean_native/apps/v2/get_apps_deployment.py
pulumi_digitalocean_native/apps/v2/get_apps_instance_size.py
pulumi_digitalocean_native/apps/v2/get_apps_log.py
pulumi_digitalocean_native-0.0.8.dist-info/METADATA
pulumi_digitalocean_native-0.0.8.dist-info/WHEEL
pulumi_digitalocean_native-0.0.8.dist-info/top_level.txt
pulumi_digitalocean_native-0.0.8.dist-info/RECORD
